jjrawlins_cdk_ami_builder/__init__.py
jjrawlins_cdk_ami_builder/py.typed
jjrawlins_cdk_ami_builder/_jsii/__init__.py
jjrawlins_cdk_ami_builder/_jsii/cdk-ami-builder@0.0.148.jsii.tgz
jjrawlins_cdk_ami_builder-0.0.148.dist-info/LICENSE
jjrawlins_cdk_ami_builder-0.0.148.dist-info/METADATA
jjrawlins_cdk_ami_builder-0.0.148.dist-info/WHEEL
jjrawlins_cdk_ami_builder-0.0.148.dist-info/top_level.txt
jjrawlins_cdk_ami_builder-0.0.148.dist-info/RECORD
