Metadata-Version: 2.1
Name: jjrawlins-cdk-ami-builder
Version: 0.0.148
Summary: Creates an EC2 AMI using an Image Builder Pipeline and returns the AMI ID.
Home-page: https://github.com/JaysonRawlins/cdk-ami-builder.git
Author: Jayson Rawlins<jayson.rawlins@gmail.com>
License: Apache-2.0
Project-URL: Source, https://github.com/JaysonRawlins/cdk-ami-builder.git
Classifier: Intended Audience :: Developers
Classifier: Operating System :: OS Independent
Classifier: Programming Language :: JavaScript
Classifier: Programming Language :: Python :: 3 :: Only
Classifier: Programming Language :: Python :: 3.9
Classifier: Programming Language :: Python :: 3.10
Classifier: Programming Language :: Python :: 3.11
Classifier: Typing :: Typed
Classifier: Development Status :: 5 - Production/Stable
Classifier: License :: OSI Approved
Requires-Python: ~=3.9
License-File: LICENSE
Requires-Dist: aws-cdk-lib <3.0.0,>=2.85.0
Requires-Dist: constructs <11.0.0,>=10.0.5
Requires-Dist: jsii <2.0.0,>=1.126.0
Requires-Dist: publication >=0.0.3
Requires-Dist: typeguard ==2.13.3
